img2zarr/__init__.py
img2zarr/cli.py
img2zarr/img2zarr.py
img2zarr-0.0.0.dist-info/LICENSE
img2zarr-0.0.0.dist-info/METADATA
img2zarr-0.0.0.dist-info/WHEEL
img2zarr-0.0.0.dist-info/entry_points.txt
img2zarr-0.0.0.dist-info/top_level.txt
img2zarr-0.0.0.dist-info/RECORD
